{
  "message": "Account groups fetched successfully",
  "success": true,
  "timestamp": "2025-11-28T10:30:00+05:30",
  "cache": true,
  "data": [
    {
      "id": 4000,
      "name": "Cash",
      "description": "Physical cash and petty cash",
      "icon": "piggy_bank",
      "isSystemDefault": true,
      "color": "#FFC107"
    },
    {
      "id": 4001,
      "name": "Bank Accounts",
      "description": "Savings and current accounts",
      "icon": "piggybank_filled",
      "isSystemDefault": true,
      "color": "#2196F3"
    },
    {
      "id": 4002,
      "name": "Credit Cards",
      "description": "Credit card liabilities",
      "icon": "transactions",
      "isSystemDefault": true,
      "color": "#E91E63"
    },
    {
      "id": 4003,
      "name": "Investments",
      "description": "Stocks, mutual funds, and other investments",
      "icon": "stats",
      "isSystemDefault": false,
      "color": "#4CAF50"
    },
    {
      "id": 4004,
      "name": "Loans & Debts",
      "description": "Personal loans, mortgages, and liabilities",
      "icon": "warning",
      "isSystemDefault": true,
      "color": "#F44336"
    },
    {
      "id": 4005,
      "name": "Digital Wallets",
      "description": "UPI wallets and e-wallets",
      "icon": "transfer",
      "isSystemDefault": false,
      "color": "#9C27B0"
    }
  ]
}